ors3handler/__init__.py
ors3handler/ors3handler.py
ors3handler-0.0.31.dist-info/LICENSE.txt
ors3handler-0.0.31.dist-info/METADATA
ors3handler-0.0.31.dist-info/WHEEL
ors3handler-0.0.31.dist-info/top_level.txt
ors3handler-0.0.31.dist-info/RECORD
