Metadata-Version: 2.1
Name: ors3handler
Version: 0.0.31
Summary: AWS S3 Data Management.
Home-page: https://github.com/leonardomra/s3handler
Author: Leonardo de Araújo
Author-email: dearaujo@uni-bremen.de
License: UNKNOWN
Platform: UNKNOWN
Classifier: Programming Language :: Python :: 3
Classifier: License :: OSI Approved :: MIT License
Classifier: Operating System :: OS Independent
Requires-Python: >=3.6
License-File: LICENSE.txt
Requires-Dist: boto3 (==1.14.25)
Requires-Dist: botocore (==1.17.47)
Requires-Dist: Werkzeug (<1.0.1,>=0.16.1)
